blow/__init__.py
blow/__main__.py
blow-0.1.0.dist-info/entry_points.txt
blow-0.1.0.dist-info/COPYING
blow-0.1.0.dist-info/WHEEL
blow-0.1.0.dist-info/METADATA
blow-0.1.0.dist-info/RECORD
